Metadata-Version: 2.1
Name: pdfjinjax
Version: 1.2.2
Summary: Use jinja templates to fill and sign PDF forms, based on rammie/pdfjinja with a few enhancements.
Home-page: http://github.com/edgaraafelix/pdfjinjax/
Author: Edgar Felix
Author-email: eaafelix@gmail.com
License: UNKNOWN
Platform: UNKNOWN
